{
	"info": {
		"_postman_id": "cf653bf9-463d-4401-9d86-6f6d436bae21",
		"name": "Loyalty",
		"schema": "https://schema.getpostman.com/json/collection/v2.1.0/collection.json"
	},
	"item": [
		{
			"name": "api-docs",
			"request": {
				"method": "GET",
				"header": [],
				"body": {},
				"url": {
					"raw": "http://localhost:3053/loyalty/customer/api-docs/v1",
					"protocol": "http",
					"host": [
						"localhost"
					],
					"port": "3053",
					"path": [
						"fif",
						"loyalty",
						"v1",
						"api-docs"
					]
				}
			},
			"response": []
		},
		{
			"name": "swagger.json",
			"request": {
				"method": "GET",
				"header": [],
				"body": {},
				"url": {
					"raw": "http://localhost:3053/loyalty/customer/api-docs/v1/swagger.json",
					"protocol": "http",
					"host": [
						"localhost"
					],
					"port": "3053",
					"path": [
						"fif",
						"loyalty",
						"v1",
						"swagger.json"
					]
				}
			},
			"response": []
		}
	]
}